defensive_network/__init__.py
defensive_network/__main__.py
defensive_network/models/__init__.py
defensive_network/models/average_position.py
defensive_network/models/expected_receiver.py
defensive_network/models/formation.py
defensive_network/models/formation_v2.py
defensive_network/models/involvement.py
defensive_network/models/meta.py
defensive_network/models/passing_network.py
defensive_network/models/responsibility.py
defensive_network/models/synchronization.py
defensive_network/models/value.py
defensive_network/models/velocity.py
defensive_network/parse/__init__.py
defensive_network/parse/drive.py
defensive_network/parse/dfb/__init__.py
defensive_network/parse/dfb/cdf.py
defensive_network/parse/dfb/meta.py
defensive_network/parse/dfb/video.py
defensive_network/tests/__init__.py
defensive_network/tests/data.py
defensive_network/tests/end_to_end/__init__.py
defensive_network/tests/end_to_end/test_drive.py
defensive_network/tests/unit/__init__.py
defensive_network/tests/unit/test_passing_network.py
defensive_network/tests/unit/test_responsibility.py
defensive_network/utility/__init__.py
defensive_network/utility/dashboards.py
defensive_network/utility/dataframes.py
defensive_network/utility/fonts.py
defensive_network/utility/general.py
defensive_network/utility/pitch.py
defensive_network/utility/stats.py
defensive_network/utility/video.py
defensive_network-0.0.8.dist-info/licenses/LICENSE
old/__init__.py
old/process_dfb_data.py
scripts/2025-06-16_check_raw_data.py
scripts/2025-08-04_compare_responsibility_models.py
scripts/2025-09-27_count_frames_etc.py
scripts/2025-09-29_sensitivity.py
scripts/2025-10-01_world_cup.py
scripts/__init__.py
scripts/check_dfb_data_quality.py
scripts/download_fifa_ratings.py
scripts/download_market_values.py
scripts/explore_metrica.py
scripts/explore_statsbomb.py
scripts/new_formation_tests.py
scripts/pfffc.py
scripts/responsibility_and_google_drive.py
scripts/sofascore_ratings.py
scripts/xt_statsbomb_correlation.py
scripts/explore/Explore_defensive_networks.py
defensive_network-0.0.8.dist-info/METADATA
defensive_network-0.0.8.dist-info/WHEEL
defensive_network-0.0.8.dist-info/top_level.txt
defensive_network-0.0.8.dist-info/RECORD
