Metadata-Version: 2.4
Name: defensive_network
Version: 0.0.8
Summary: Implementation of defensive passing networks for football (soccer) analytics.
Author-email: Jonas Bischofberger <jonas.bischofberger@univie.ac.at>, Runqing Ma <runqing.ma@univie.ac.at>
License: MIT License
Project-URL: Repository, https://github.com/jonas-bischofberger/defensive-network
Requires-Python: >=3.7
License-File: LICENSE
Requires-Dist: accessible-space
Requires-Dist: kloppy
Requires-Dist: matplotlib
Requires-Dist: mplsoccer
Requires-Dist: networkx
Requires-Dist: numpy
Requires-Dist: openpyxl
Requires-Dist: pandas
Requires-Dist: pytest
Requires-Dist: python-slugify
Requires-Dist: scikit-learn
Requires-Dist: scipy
Requires-Dist: seaborn
Requires-Dist: selenium
Requires-Dist: statsbombpy
Requires-Dist: streamlit
Requires-Dist: streamlit-profiler
Requires-Dist: tqdm
Requires-Dist: webdriver-manager
Requires-Dist: wfork-streamlit-profiler
Requires-Dist: patsy
Requires-Dist: statsmodels
Requires-Dist: opencv-python
Requires-Dist: requests
Requires-Dist: beautifulsoup4
Requires-Dist: pandera[pandas]
Requires-Dist: shapely
Requires-Dist: google-api-python-client
Requires-Dist: google-auth-httplib2
Requires-Dist: google-auth-oauthlib
Requires-Dist: memory-profiler
Requires-Dist: pingouin
Provides-Extra: dev
Requires-Dist: pytest; extra == "dev"
Requires-Dist: pytest-cov; extra == "dev"
Requires-Dist: build; extra == "dev"
Requires-Dist: twine; extra == "dev"
Requires-Dist: setuptools; extra == "dev"
Requires-Dist: tox; extra == "dev"
Dynamic: license-file
